[{"name":"3310","description":"somthing longer","brand":"nokia","price":100,"category":"smartphones","_id":"c1mu18halesc8uzo","createdAt":"2023-03-03T09:33:40.451Z","updatedAt":"2023-03-03T09:33:40.451Z","imageUrl":"http://localhost:3001/img/products/c1mu18halesc8uzo.jpg"},{"name":"3310","description":"somthing longer","brand":"nokia","price":100,"category":"phone","_id":"c1mu18i4lescbc97","createdAt":"2023-03-03T09:35:36.138Z","updatedAt":"2023-03-03T09:35:36.138Z"},{"name":"3310","description":"somthing longer","brand":"nokia","price":200,"_id":"c1mu19csleseku83","createdAt":"2023-03-03T10:38:58.562Z","updatedAt":"2023-03-03T10:38:58.562Z"}]
